[
  {
      "id": "user|de539e8b-1119-41bb-97cb-5022bd0383a6",
      "name": "Tareq Haider",
      "email": "tareq.haider@brainstation-23.com"
  },
  {
      "id": "user|e78c741c-43fd-b464-d714-cf4bbf8ea9b7",
      "name": "sufian@brainstation-23.com",
      "email": "sufian@brainstation-23.com"
  },
  {
      "id": "user|938bccb2-7b7d-4a25-9cb6-815067c9d886",
      "name": "newaz hossain",
      "email": "newaz.hossain@brainstation-23.com"
  },
  {
      "id": "user|8983c6d7-f236-432d-93fe-154ddb8c87de",
      "name": "Stian Tumyr",
      "email": "st@informatiq.no"
  },
  {
      "id": "user|b0f199a4-1c86-4336-8bc0-7625255f56fc",
      "name": "Sazzad Hossain",
      "email": "sazzad.hossain@brainstation-23.com"
  },
  {
      "id": "user|95c751ae-383f-49d6-bbb1-8011933715ec",
      "name": "andersappdev@informatiq.no",
      "email": "andersappdev@informatiq.no"
  },
  {
      "id": "user|33c983ef-0a19-451c-b5d1-802b273f30f2",
      "name": "André Nilsen",
      "email": "an@informatiq.no"
  },
  {
      "id": "user|81b7291b-1a31-4c12-b572-ee17fd2b3501",
      "name": "Tharun Krishnamoorthy",
      "email": "tharun.krishnamoorthy@halliburton.com"
  },
  {
      "id": "user|45c0a706-6b2b-44a0-81f0-f1014177fdf4",
      "name": "Abhishek Halkurki",
      "email": "abhishek.halkurki@halliburton.com"
  },
  {
      "id": "user|0ba80422-21c7-49f0-8c2c-09006ee304bc",
      "name": "Christian Test",
      "email": "christiantest@informatiq.no"
  },
  {
      "id": "user|a758f6ae-db5d-4134-8e91-0079e79f3539",
      "name": "Pavlo",
      "email": "pavlo@linkupst.com"
  },
  {
      "id": "user|308d3cfa-a72a-4591-a937-58858538e0a4",
      "name": "Orest Urban",
      "email": "orest@linkupst.com"
  },
  {
      "id": "user|60952c58-353d-43b3-903f-d8d320a378d7",
      "name": "Mehedi Hasan",
      "email": "mehedi.hasan23@brainstation-23.com"
  },
  {
      "id": "user|03f96efc-967e-42be-aa02-1e9f3fcbad57",
      "name": "uvj@informatiq.no",
      "email": "uvj@informatiq.no"
  },
  {
      "id": "user|cc68464b-0902-44fa-b795-68ea98310576",
      "name": "geologiq@mentalfish.com",
      "email": "geologiq@mentalfish.com"
  },
  {
      "id": "user|9141ebac-ccf1-46b6-bf78-44a3ccf84c16",
      "name": "Sufian",
      "email": "sufian@informatiq.no"
  },
  {
      "id": "user|75bdb37b-ac50-488d-a458-621b9c7ac403",
      "name": "Erlend Søreide",
      "email": "erlend.demo@gmail.com"
  },
  {
      "id": "user|3e5587a8-6b2f-4b7f-b370-61c8c46e24a9",
      "name": "Andre Nilsen",
      "email": "vinefin@gmail.com"
  },
  {
      "id": "user|86f1774f-f0ea-4192-95b5-2c82fc86e2cb",
      "name": "UV Jensen",
      "email": "uvjabp@outlook.com"
  },
  {
      "id": "user|2cfd98e9-f765-42b9-a4b9-b945d1d6a0d7",
      "name": "Petter",
      "email": "petter@goontech.no"
  },
  {
      "id": "user|87808f5d-5d91-46e8-b8b0-156b15ef8bb6",
      "name": "Ulf Vegard Jensen",
      "email": "ulf.vegard.jensen@akerbp.com"
  },
  {
      "id": "user|7385c37e-4717-4505-81a1-9c6b6c85ad5f",
      "name": "Tarek Arakili",
      "email": "tarek.arakili@akerbp.com"
  },
  {
      "id": "user|378e74a8-4a46-4d6c-8dc2-0ec9ec322399",
      "name": "Utpaul Sarkar",
      "email": "utpaul.sarkar@brainstation-23.com"
  },
  {
      "id": "user|47a7ce24-5fa0-4abd-96b8-e1895e41a148",
      "name": "Roy Subrata",
      "email": "roy.subrata@brainstation-23.com"
  },
  {
      "id": "user|a604a920-fb98-4756-83fa-3fe00101c4bc",
      "name": "Asif Jubair",
      "email": "asif.jubair@brainstation-23.com"
  },
  {
      "id": "user|67a22e18-613b-4fc6-86e6-caa8dbe3275b",
      "name": "Yaryna",
      "email": "yaryna@linkupst.com"
  },
  {
      "id": "user|426b8f14-7d07-41d3-9721-f29d641d7125",
      "name": "Tazbir",
      "email": "tazbir@brainstation-23.com"
  },
  {
      "id": "user|6d0d46d3-1606-4939-b82f-8f8079e3de57",
      "name": "Daria Grigoriuk",
      "email": "daria@informatiq.no"
  },
  {
      "id": "user|c51bab8c-ea3c-4f92-b6a1-c282544f8158",
      "name": "Muhammad Ramzan",
      "email": "muhammad.ramzan@brainstation23.com"
  },
  {
      "id": "user|846f7ebb-f0e2-4ef1-bf0e-b57e86bd448c",
      "name": "Ramzan Ali",
      "email": "ramzan.ali.suzan@hotmail.com"
  },
  {
      "id": "user|af2aff01-8ef5-44f6-bc13-a04c184816a3",
      "name": "Nadia Zaman",
      "email": "nadia.zaman@brainstation-23.com"
  },
  {
      "id": "user|e8063443-2cde-48d3-9d5a-f38534f9f599",
      "name": "Prottoy Paul",
      "email": "prottoy.paul@brainstation-23.com"
  },
  {
      "id": "user|bf182eb6-686c-4806-aa7a-09a66e12c1ab",
      "name": "Raihan",
      "email": "raihanuzzaman@brainstation-23.com"
  },
  {
      "id": "user|9c03da94-d967-4bf9-9bf9-d56065f936ce",
      "name": "Christian Elle",
      "email": "cedevabp@informatiq.no"
  },
  {
      "id": "user|5cd323c3-fe27-429f-a29c-bde44fcab5d3",
      "name": "Roni Kumer",
      "email": "roni.kumer@brainstation-23.com"
  },
  {
      "id": "user|1d0cfb1d-20c5-445b-a982-b9f3282a037a",
      "name": "Wasif Mustahid",
      "email": "wasif.mustahid@brainstation-23.com"
  },
  {
      "id": "user|2de30db4-adf4-4dda-9a50-989f5eec22d2",
      "name": "Md. Al-Amin",
      "email": "md.al-amin@brainstation-23.com"
  },
  {
      "id": "user|bdb33af4-ef07-428a-9832-1da01b9d90d4",
      "name": "Christian Elle",
      "email": "ce@informatiq.no"
  },
  {
      "id": "user|da56f075-82e3-431c-ac7d-34543eed4f2f",
      "name": "Sanjit Majumdar",
      "email": "sanjit.majumdar@brainstation-23.com"
  },
  {
      "id": "user|b140b6ee-a809-473e-bd78-c8658397c5e6",
      "name": "Fabian Schnuer",
      "email": "fabian@gohde.no"
  },
  {
      "id": "user|8614026a-6821-47c6-8e37-92d99942ee7d",
      "name": "Natcha Uthaug",
      "email": "nu@informatiq.no"
  },
  {
      "id": "user|9dded2c0-015c-4073-9a24-9a4e5a6a36ad",
      "name": "Other User (No access)",
      "email": "other-user@informatiq.no"
  },
  {
      "id": "user|3cb13cec-3ad0-4b10-af38-605029ef0b67",
      "name": "Hanidur Rhaman",
      "email": "hamidur.rhaman@brainstation-23.com"
  },
  {
      "id": "user|05ee2f6f-61ac-4030-b857-b6bed9358db7",
      "name": "Ulf Vegard Jensen",
      "email": "uvjappdev@gmail.com"
  },
  {
      "id": "user|5dc8a6de-a152-4784-80ce-832c57b0a7cf",
      "name": "San Maju",
      "email": "sanjit.cse.1@gmail.com"
  },
  {
      "id": "user|590d087a-b057-4f11-9290-8d44556ca87b",
      "name": "Hasan Ahmed",
      "email": "hasan.ahmed@brainstation-23.com"
  },
  {
      "id": "user|7420b326-f71b-489c-8626-c6c98b284305",
      "name": "DDP User",
      "email": "ddp-user@informatiq.no"
  },
  {
      "id": "user|90e8bf28-5b02-4a13-b0e3-7d47b755813a",
      "name": "Ottar Henanger",
      "email": "oh@informatiq.no"
  },
  {
      "id": "user|1c28ae75-5363-4947-b5f1-c497a71fa4b9",
      "name": "Anish Jose",
      "email": "aj@informatiq.no"
  },
  {
      "id": "user|974f95aa-e412-4808-b973-c0bbed029ad7",
      "name": "Madhav Roman",
      "email": "madhav@gmail.com"
  },
  {
      "id": "user|9cfa9f45-ef84-4613-bda7-469d70c4c916",
      "name": "Hakim Amea",
      "email": "hakim@gmail.com"
  },
  {
      "id": "user|e084559e-243b-469a-b637-9bfc8064b88b",
      "name": "Sanjit Majumdar",
      "email": "sanjit.cse.3@gmail.com"
  },
  {
      "id": "user|ca61102c-77f3-47b9-bbd6-1f938d2369be",
      "name": "Syed Adib Arman",
      "email": "syed.adib@brainstation-23.com"
  },
  {
      "id": "user|67c665ad-698c-4068-9628-5b88a011f6d8",
      "name": "Mash Burnded",
      "email": "sanjit.cse.2@gmail.com"
  },
  {
      "id": "user|29c59b7f-dbf1-43f3-a7c2-d9822e50db03",
      "name": "Christian Elle",
      "email": "christian.elle@akerbp.com"
  },
  {
      "id": "user|d04dfbb6-0d18-462d-9263-cdeb9dab2318",
      "name": "tim jim",
      "email": "tim@yopmail.com"
  },
  {
      "id": "user|5c7f8434-b8ac-4969-af37-53ac10e4257b",
      "name": "Ottar Henanger",
      "email": "ottar.henanger@akerbp.com"
  },
  {
      "id": "user|274699da-18e1-4397-af68-2192f21f772f",
      "name": "Samantha Wilkins",
      "email": "samantha@gmail.com"
  },
  {
      "id": "user|39b72bd8-7094-4a66-b2d8-a298e0bb429b",
      "name": "Cory Anderson",
      "email": "cory@gmail.com"
  },
  {
      "id": "user|614006ae-250e-48ad-8f1b-aac6e4551515",
      "name": "test wellbook5",
      "email": "testwellbook5@yopmail.com"
  },
  {
      "id": "user|d2d83739-870a-4dd7-a905-acf10f5ad0b9",
      "name": "test wellbook6",
      "email": "testwellbook6@yopmail.com"
  },
  {
      "id": "user|21c84e52-45b2-4b8e-b7a9-642e6d9ada69",
      "name": "test wellbook3",
      "email": "testwellbook3@yopmail.com"
  },
  {
      "id": "user|b25d2bc0-a067-4575-8f3f-3b3a4747ba47",
      "name": "Erlend Søreide (AkerBP)",
      "email": "erlend.akerbp@gmail.com"
  },
  {
      "id": "user|c77120b7-63f4-467a-93fd-75f2050c6066",
      "name": "pina rim",
      "email": "rafi01@yopmail.com"
  },
  {
      "id": "user|fac42be1-a3c9-41ec-9772-ad80b890a67f",
      "name": "Test wellbook123",
      "email": "testwellbook123@yopmail.com"
  },
  {
      "id": "user|21d8d31c-07ce-43a1-a884-4c7f9ef3d471",
      "name": "Erlend Søreide",
      "email": "es@informatiq.no"
  },
  {
      "id": "user|4dfeeeb2-17d3-42de-9970-edf3bb9c8f3e",
      "name": "Test User",
      "email": "test@informatiq.no"
  },
  {
      "id": "user|31f9d048-46f9-4054-8cba-52e574d6191c",
      "name": "wellbook varenergi4",
      "email": "wellbookvarenergi4@yopmail.com"
  },
  {
      "id": "user|b51c0f6e-15d8-4692-9377-0716fce2f686",
      "name": "Bayzed Meer",
      "email": "bayzed.meer@brainstation-23.com"
  },
  {
      "id": "user|267e40ee-40c6-4eef-8280-c21681260270",
      "name": "Test User",
      "email": "test-ottar@informatiq.no"
  },
  {
      "id": "user|2504dd84-669e-434f-a85e-e6b84fb4d588",
      "name": "Md. Imran Hossain",
      "email": "imran@brainstation-23.com"
  },
  {
      "id": "user|a9b906d4-f23a-4ced-bd37-cf4bc27893f5",
      "name": "Abdullah Fahad",
      "email": "abdullah.fahad@brainstation-23.com"
  },
  {
      "id": "user|55accf04-7e78-4e0c-9060-4283a88d2af3",
      "name": "Sharmin Akter",
      "email": "sharmin.akter@brainstation-23.com"
  },
  {
      "id": "user|7ff7d9a8-c8d1-4c2d-9893-12c8d80c1560",
      "name": "Imran Hossain",
      "email": "mihemu5@gmail.com"
  },
  {
      "id": "user|dc48776a-e93a-4d07-a13b-58388d923f08",
      "name": "Arafath Hossen Santo",
      "email": "arafath.santo@brainstation-23.com"
  },
  {
      "id": "user|3553cf05-1a3f-4976-b074-76f639dd6a62",
      "name": "Abdullah Al Zaied",
      "email": "al.zaied@brainstation-23.com"
  },
  {
      "id": "user|91355e32-1fb2-404c-8553-73cd896dc866",
      "name": "Anders Langøy",
      "email": "al@informatiq.no"
  },
  {
      "id": "user|cfca97a9-2313-433b-8078-052b7a68aae3",
      "name": "Sharmin Dolly",
      "email": "sharmin123-12@yopmail.com"
  },
  {
      "id": "user|b9c9d832-e264-43d1-b088-401afe7e18d2",
      "name": "New Add",
      "email": "newwellbookuser02@yopmail.com"
  },
  {
      "id": "user|9b3f21e7-0b8a-43d7-a4c0-e6f71838298f",
      "name": "Anish Jose",
      "email": "anishjose27@gmail.com"
  },
  {
      "id": "user|6835798d-8320-4ff5-8571-ff1295fc6cd5",
      "name": "Ordin Husa",
      "email": "oh@gs1.no"
  }
]
